<?xml version="1.0" encoding="utf-8" ?>
<dwsync>
<file name="bootstrap.css" server="42.112.16.97//var/www/html/vinastudy.vn/" local="131280237720000000" remote="131280237720000000" Dst="0" />
<file name="bootstrap.css.map" server="42.112.16.97//var/www/html/vinastudy.vn/" local="131280237720000000" remote="131280237720000000" Dst="0" />
<file name="bootstrap-theme.min.css" server="42.112.16.97//var/www/html/vinastudy.vn/" local="131280237720000000" remote="131280237720000000" Dst="0" />
<file name="bootstrap.min.css" server="42.112.16.97//var/www/html/vinastudy.vn/" local="131280237720000000" remote="131280237720000000" Dst="0" />
<file name="bootstrap-theme.css.map" server="42.112.16.97//var/www/html/vinastudy.vn/" local="131280237720000000" remote="131280237720000000" Dst="0" />
<file name="bootstrap-theme.min.css.map" server="42.112.16.97//var/www/html/vinastudy.vn/" local="131280237720000000" remote="131280237720000000" Dst="0" />
<file name="bootstrap-theme.css" server="42.112.16.97//var/www/html/vinastudy.vn/" local="131280237730000000" remote="131280237730000000" Dst="0" />
<file name="bootstrap.min.css.map" server="42.112.16.97//var/www/html/vinastudy.vn/" local="131280237730000000" remote="131280237730000000" Dst="0" />
</dwsync>